gccdpune.py
gccdpune-1.0.2.dist-info/licenses/LICENSE
gccdpune-1.0.2.dist-info/METADATA
gccdpune-1.0.2.dist-info/WHEEL
gccdpune-1.0.2.dist-info/entry_points.txt
gccdpune-1.0.2.dist-info/top_level.txt
gccdpune-1.0.2.dist-info/RECORD
