Metadata-Version: 2.4
Name: gccdpune
Version: 1.0.2
Summary: Interactive CLI for Google Cloud Community Day Pune 2025
Home-page: https://github.com/Gitesh08/gccdpune
Author: Gitesh Mahadik
Author-email: gmahadik8080@gmail.com
Classifier: Programming Language :: Python :: 3
Classifier: License :: OSI Approved :: MIT License
Classifier: Operating System :: OS Independent
Requires-Python: >=3.6
License-File: LICENSE
Requires-Dist: colorama>=0.4.6
Dynamic: author
Dynamic: author-email
Dynamic: classifier
Dynamic: description
Dynamic: description-content-type
Dynamic: home-page
Dynamic: license-file
Dynamic: requires-dist
Dynamic: requires-python
Dynamic: summary
